{
  "$schema": "./omm.schema.json",
  "dispatch": [
    ["signature", {
      "ad5f04b9": "AMOS_ProV2_00__CmpLineCLI",
      "8fd0e634": "AMOS_ProV2_00__PlusF",
      "febdf0fc": "AMOS_ProV2_00__MoinsF",
      "1c250a8c": "AMOS_ProV2_00__MultE",
      "e0255eb9": "AMOS_ProV2_00__MultF",
      "8f08b818": "AMOS_ProV2_00__DiviseE",
      "a4752bf3": "AMOS_ProV2_00__DiviseF",
      "ce7c4a40": "AMOS_ProV2_00__Puissance",
      "1e913308": "AMOS_ProV2_00__Modulo",
      "25e6e285": "AMOS_ProV2_00__Chaine_Compare",
      "430501bf": "AMOS_ProV2_00__Test_PaSaut",
      "5f0036c1": "AMOS_ProV2_00__Test_Normal",
      "7defda32": "AMOS_ProV2_00__Test_Force",
      "a1e2708b": "AMOS_ProV2_00_PrgUnder",
      "eedf1cde": "AMOS_ProV2_00_CloseEditor",
      "f34678c6": "AMOS_ProV2_00_KillEditor",
      "5cb144de": "AMOS_ProV2_00_PrgState",
      "cdaa4f85": "AMOS_ProV2_00_BreakOn",
      "e9831880": "AMOS_ProV2_00_BreakOff",
      "e7571f72": "AMOS_ProV2_00__InOnBreak",
      "de855a6a": "AMOS_ProV2_00__InOnError",
      "6bd1be8f": "AMOS_ProV2_00__InOnErrorGoto",
      "afd186c1": "AMOS_ProV2_00__InOnErrorProc",
      "fd507870": "AMOS_ProV2_00__InResumeLabel",
      "5b012a2c": "AMOS_ProV2_00__InResumeLabel1",
      "376237d5": "AMOS_ProV2_00__InResume",
      "6597a3d7": "AMOS_ProV2_00__InResume1",
      "e1726a35": "AMOS_ProV2_00_ResumeNext",
      "7cd814bc": "AMOS_ProV2_00_Trap",
      "1159de7d": "AMOS_ProV2_00_Errtrap",
      "7ad6d53e": "AMOS_ProV2_00_EveryOff",
      "2fdd19d2": "AMOS_ProV2_00_EveryOn",
      "68a3f409": "AMOS_ProV2_00__InNext",
      "ff9c3e74": "AMOS_ProV2_00__InNextF",
      "3c5f5aea": "AMOS_ProV2_00_Return",
      "95782b76": "AMOS_ProV2_00__DProc1",
      "b076c824": "AMOS_ProV2_00__DProc2F",
      "13e8e189": "AMOS_ProV2_00__DProc2D",
      "a55fd477": "AMOS_ProV2_00__FProc",
      "a95f3d8d": "AMOS_ProV2_00_Array",
      "3c5a3e0e": "AMOS_ProV2_00__InSwap",
      "a0690e11": "AMOS_ProV2_00__InSwapD",
      "6525b4b2": "AMOS_ProV2_00_Max",
      "bd983f40": "AMOS_ProV2_00__FnMinS",
      "5e40b3e6": "AMOS_ProV2_00_Min",
      "d1fe36d9": "AMOS_ProV2_00__InAdd4",
      "de275437": "AMOS_ProV2_00_Sort",
      "19401ef1": "AMOS_ProV2_00_Match",
      "7d0cde51": "AMOS_ProV2_00__InRestore",
      "33dbb0aa": "AMOS_ProV2_00__CRet",
      "41e60f7f": "AMOS_ProV2_00__PrintE",
      "eb095766": "AMOS_ProV2_00__PrintF",
      "a54cf444": "AMOS_ProV2_00__PrintS",
      "c52841df": "AMOS_ProV2_00__PrintX",
      "41fabd93": "AMOS_ProV2_00__CRPrint",
      "8054f4e1": "AMOS_ProV2_00__PrtRet",
      "2b9c1dd6": "AMOS_ProV2_00__PrtVir",
      "03b9fc30": "AMOS_ProV2_00__UsingC",
      "097e4f7f": "AMOS_ProV2_00__UsingS",
      "9c44627b": "AMOS_ProV2_00_DefaultPalette",
      "01fb44a8": "AMOS_ProV2_00__Plt",
      "811b0e9a": "AMOS_ProV2_00_Bset",
      "e75c31ff": "AMOS_ProV2_00__InBset1",
      "910a52c7": "AMOS_ProV2_00_Bclr",
      "c81389ad": "AMOS_ProV2_00__InBclr1",
      "66e21b1d": "AMOS_ProV2_00_Bchg",
      "780984b4": "AMOS_ProV2_00__InBchg1",
      "070d44a8": "AMOS_ProV2_00_RorB",
      "9ca576d4": "AMOS_ProV2_00__InRorB1",
      "247a2102": "AMOS_ProV2_00_RorW",
      "c1137694": "AMOS_ProV2_00__InRorW1",
      "1ab953d1": "AMOS_ProV2_00_RorL",
      "c7340393": "AMOS_ProV2_00__InRorL1",
      "7ba00478": "AMOS_ProV2_00_RolB",
      "c21a74c5": "AMOS_ProV2_00__InRolB1",
      "6378f510": "AMOS_ProV2_00_RolW",
      "8ae218de": "AMOS_ProV2_00__InRolW1",
      "41b3256f": "AMOS_ProV2_00_RolL",
      "342e297e": "AMOS_ProV2_00__InRolL1",
      "fe5c2a5c": "AMOS_ProV2_00_Call",
      "381e2411": "AMOS_ProV2_00_Val",
      "22feaaf5": "AMOS_ProV2_00_MenuDel",
      "25a1b540": "AMOS_ProV2_00__IntToFl1",
      "51d7c285": "AMOS_ProV2_00__DIntToFl1",
      "f750ab3f": "AMOS_ProV2_00__IntToFl2",
      "4fff3966": "AMOS_ProV2_00__DIntToFl2",
      "26a0f508": "AMOS_ProV2_00__FlToInt1",
      "2884dab6": "AMOS_ProV2_00__DFlToInt1",
      "7f4eed04": "AMOS_ProV2_00__FlToInt2",
      "39993529": "AMOS_ProV2_00__DFlToInt2",
      "4de69b9e": "AMOS_ProV2_00__Float_Compare",
      "8a48486f": "AMOS_ProV2_00__DFloat_Compare",
      "7a508c3c": {
        "4a6d 0a04 6602 4e75 2003 260e": "AMOS_ProV2_00__FFAngle",
        "4a6d 0a04 6602 4e75 2003 2204": "AMOS_ProV2_00__FAngleD"
      },
      "c321082d": "AMOS_ProV2_00_Param_F",
      "28dacc2f": "AMOS_ProV2_00__FnParamD",
      "77235d59": "AMOS_ProV2_00__FnMaxF",
      "d6523246": "AMOS_ProV2_00__FnMaxD",
      "f50dfcad": "AMOS_ProV2_00__FnMinF",
      "0b017f6b": "AMOS_ProV2_00__FnMinD",
      "80d275c7": "AMOS_ProV2_00_Errn",
      "4da71060": "AMOS_ProV2_00_Err",
      "2efb9564": "AMOS_ProV2_00_Sgn",
      "75e65823": "AMOS_ProV2_00_Str",
      "951d1444": "AMOS_ProV2_00_Abs",
      "9d6cf174": "AMOS_ProV2_00_Tan",
      "c11ada20": "AMOS_ProV2_00_Sqr",
      "c65b2522": "AMOS_ProV2_00_Log",
      "85307a00": "AMOS_ProV2_00_Ln",
      "18af78d7": "AMOS_ProV2_00_Exp",
      "28e78e8f": "AMOS_ProV2_00_Sin",
      "297817a9": "AMOS_ProV2_00_Cos",
      "70406a5e": "AMOS_ProV2_00_Asin",
      "81f023fa": "AMOS_ProV2_00_Acos",
      "586d42e4": "AMOS_ProV2_00_Atan",
      "6be391fa": "AMOS_ProV2_00_Hsin",
      "117556bc": "AMOS_ProV2_00_Hcos",
      "115eda6c": "AMOS_ProV2_00_Htan",
      "d8dfeb45": "AMOS_ProV2_00_Radian",
      "e7362fae": "AMOS_ProV2_00_Degree",
      "f69478ca": "AMOS_ProV2_00_Fix",
      "72c4b871": "AMOS_ProV2_00_Rnd",
      "ce766270": "AMOS_ProV2_00_Randomize",
      "40381a45": "AMOS_ProV2_00_Timer_set",
      "112f9f57": "AMOS_ProV2_00_Timer_get",
      "3ec14b5e": "AMOS_ProV2_00_Pi",
      "eaf68ac2": "AMOS_ProV2_00_Wait",
      "e27e9435": "AMOS_ProV2_00_MultiWait",
      "dea6297e": "AMOS_ProV2_00_WaitVbl",
      "1fc1b6dc": "AMOS_ProV2_00_WaitKey",
      "5ba4bf93": "AMOS_ProV2_00_KeySpeed",
      "fe1a0b62": "AMOS_ProV2_00_Param_S",
      "35bffdf7": "AMOS_ProV2_00_Param_I",
      "1becc20c": "AMOS_ProV2_00_ListBank",
      "4379d99d": "AMOS_ProV2_00_Erase",
      "336556f8": [
        ["match", "6100"],
        "follow-rel",
        {
          "48e7 2020 246d 05ea 2412 671a 2442 2412": "AMOS_ProV2_00_EraseTemp",
          "48e7 2020 246d 05ea 2412 6710 2442 2412": "AMOS_ProV2_00_EraseAll"
        }
      ],
      "1d918277": "AMOS_ProV2_00_BankSwap",
      "c35c6d43": "AMOS_ProV2_00_Bstart_I",
      "96961fea": "AMOS_ProV2_00_Blength",
      "8607588a": "AMOS_ProV2_00_Bgrab",
      "1c4fb184": "AMOS_ProV2_00_Bsend",
      "9805742e": [
        ["match", "6100"],
        "follow-rel",
        ["match", "48e7 c000"],
        {
          "7001": "AMOS_ProV2_00_InsSprite",
          "7002": "AMOS_ProV2_00_InsIcon"
        }
      ],
      "0b56254a": [
        ["match", "2703"],
        "tail-call",
        ["match", "6100"],
        "follow-rel",
        ["match", "48e7 c000"],
        {
          "7001": "AMOS_ProV2_00_DelSprite_I",
          "7002": "AMOS_ProV2_00_DelIcon_I"
        }
      ],
      "16fe4ec1": [
        ["match", "6100"],
        "follow-rel",
        ["match", "48e7 c000"],
        {
          "7001": "AMOS_ProV2_00_DelSprite_II",
          "7002": "AMOS_ProV2_00_DelIcon_II"
        }
      ],
      "1c70cfbc": "AMOS_ProV2_00_ReserveAsWork",
      "77a0f78a": "AMOS_ProV2_00_ReserveAsChipWork",
      "51cbdad6": "AMOS_ProV2_00_ReserveAsData",
      "3967c415": "AMOS_ProV2_00_ReserveAsChipData",
      "bfdb677c": "AMOS_ProV2_00_BankShrink",
      "d2270913": "AMOS_ProV2_00_Start",
      "25d0746f": "AMOS_ProV2_00_Length",
      "66bacd37": "AMOS_ProV2_00_ChipFree",
      "30a3b984": "AMOS_ProV2_00_FastFree",
      "32888b5a": "AMOS_ProV2_00_Copy",
      "33357239": "AMOS_ProV2_00_Fill",
      "91978d72": "AMOS_ProV2_00_Hunt",
      "09fc96f1": "AMOS_ProV2_00_Areg_set_I",
      "64832401": "AMOS_ProV2_00_Areg_get",
      "7fa7b436": "AMOS_ProV2_00_Dreg_set_I",
      "928df04d": "AMOS_ProV2_00_Dreg_get_I",
      "ca774552": "AMOS_ProV2_00_Poke_II",
      "2bbb1ebf": "AMOS_ProV2_00_Doke",
      "748101da": "AMOS_ProV2_00_Loke",
      "d3780129": "AMOS_ProV2_00_Peek_I_I",
      "25afe960": "AMOS_ProV2_00_Deek",
      "39e2c81a": "AMOS_ProV2_00_Leek",
      "eafb2381": "AMOS_ProV2_00_Poke_IS",
      "414b7a61": "AMOS_ProV2_00_Peek_II_S",
      "60528491": "AMOS_ProV2_00_Peek_IIS_S",
      "55fc279d": "AMOS_ProV2_00_Execall",
      "b5101354": "AMOS_ProV2_00_Gfxcall",
      "d211b221": "AMOS_ProV2_00_Doscall",
      "ca279d84": "AMOS_ProV2_00_Intcall",
      "cf7e2a96": "AMOS_ProV2_00_LibOpen",
      "1b911865": "AMOS_ProV2_00_LibClose",
      "a19cbb73": "AMOS_ProV2_00_LibClose_I",
      "fe602fe2": "AMOS_ProV2_00_LibCall",
      "e39f2684": [
        ["match", "2003 6100"],
        "follow-rel",
        ["match", "b0bc 0000 0007 6200"],
        ["skip", 1],
        {
          "e548": "AMOS_ProV2_00_LibBase",
          "c0fc": "AMOS_ProV2_00_DevBase"
        }
      ],
      "4ecf0450": "AMOS_ProV2_00_DevOpen",
      "cddf82e6": "AMOS_ProV2_00_DevClose",
      "0d67e787": "AMOS_ProV2_00_DevClose_I",
      "da156c06": [
        ["match", "201b 6100"],
        ["skip", 1],
        ["match", "2003"],
        "tail-call",
        ["match", "6100"],
        ["skip", 1],
        {
          "2f0e 2c78 0004 48e7 8040 0c2a 0002 0009 6608 4eae fe26 4cd7 0201 3340 001c 4eae fe38": "AMOS_ProV2_00_DevDo",
          "2f0e 2c78 0004 48e7 8040 0c2a 0002 0009 6608 4eae fe26 4cd7 0201 3340 001c 4eae fe32": "AMOS_ProV2_00_DevSend"
        }
      ],
      "d7a536e9": "AMOS_ProV2_00_DevAbort",
      "c4d9a5c6": "AMOS_ProV2_00_DevCheck",
      "da463b22": "AMOS_ProV2_00_Exec",
      "89d7e027": "AMOS_ProV2_00_Save_SI",
      "205847a6": "AMOS_ProV2_00_Save_S",
      "9d32f761": "AMOS_ProV2_00_Load_S",
      "7d0ed2da": "AMOS_ProV2_00_Load_SI",
      "bc15b9d4": "AMOS_ProV2_00_Pload",
      "35596883": "AMOS_ProV2_00_Bload",
      "97359051": "AMOS_ProV2_00_Bsave",
      "cc8f0b60": "AMOS_ProV2_00_MaskIff",
      "1ba816a4": "AMOS_ProV2_00_Picture",
      "ef305536": "AMOS_ProV2_00_LoadIff_S",
      "b29d1154": "AMOS_ProV2_00_LoadIff_SI",
      "9870829d": "AMOS_ProV2_00_FrameLoad_II",
      "a36cfc4b": "AMOS_ProV2_00_FrameLoad_III",
      "c9823438": "AMOS_ProV2_00_FrameLength_I",
      "fd5f9425": "AMOS_ProV2_00_FrameLength_II",
      "dae0d6ff": "AMOS_ProV2_00_FramePlay_II",
      "9f68a43a": "AMOS_ProV2_00_FramePlay_III",
      "bd12c224": "AMOS_ProV2_00_FrameSkip_I",
      "9514b5ac": "AMOS_ProV2_00_FrameSkip_II",
      "74126722": "AMOS_ProV2_00_IffAnim_SI",
      "4e24b92b": "AMOS_ProV2_00_IffAnim_SII",
      "7766c6f2": "AMOS_ProV2_00_FrameParam",
      "479a656f": "AMOS_ProV2_00_SaveIff_S",
      "59139319": "AMOS_ProV2_00_SaveIff_SI",
      "8eddb080": "AMOS_ProV2_00_SetInput",
      "ff22569e": "AMOS_ProV2_00_Input_I_S",
      "e498e8c2": "AMOS_ProV2_00_Input_II_S",
      "f702e5cb": "AMOS_ProV2_00_Dir_set",
      "2082cae8": "AMOS_ProV2_00_Dir_get",
      "ede731d4": "AMOS_ProV2_00_Parent",
      "dee8277b": "AMOS_ProV2_00_Kill",
      "a8c28118": "AMOS_ProV2_00_Rename",
      "c128b5c9": "AMOS_ProV2_00_Mkdir",
      "94ecb198": "AMOS_ProV2_00_Drive",
      "6a67f24c": "AMOS_ProV2_00_Dfree",
      "b378e880": "AMOS_ProV2_00_DiscInfo",
      "bb26ff81": "AMOS_ProV2_00_Port",
      "d8ae2f0a": "AMOS_ProV2_00_OpenPort",
      "9fb049f1": "AMOS_ProV2_00_OpenOut",
      "74e79ea9": "AMOS_ProV2_00_OpenIn",
      "e2676ad6": "AMOS_ProV2_00_Lof",
      "4e3126de": "AMOS_ProV2_00_Pof_set_I",
      "6ad65c3a": "AMOS_ProV2_00_Pof_get_I",
      "76ccf6c8": "AMOS_ProV2_00_Eof",
      "3d380b39": "AMOS_ProV2_00_Close_I",
      "0e8b664b": [
        ["match", "6100"],
        "follow-rel",
        {
          "45ed": "AMOS_ProV2_00_Close",
          "48e7": "AMOS_ProV2_00_OnMenuDel"
        }
      ],
      "e7afc39d": "AMOS_ProV2_00_OpenRandom",
      "2831e23f": "AMOS_ProV2_00_Append",
      "51697573": "AMOS_ProV2_00_Get_II_V",
      "a51b2d2d": "AMOS_ProV2_00_Put",
      "f88fcd9f": "AMOS_ProV2_00_SetDir_IS",
      "18788b6d": "AMOS_ProV2_00_SetDir_I",
      "97465485": "AMOS_ProV2_00_DevFirst",
      "8eb52f6a": "AMOS_ProV2_00_DirFirst",
      "22a0eef0": "AMOS_ProV2_00_PrgNext",
      "842bdaf5": "AMOS_ProV2_00_Assign",
      "ea8147d1": "AMOS_ProV2_00_Exist",
      "29636ea7": "AMOS_ProV2_00_LdirW",
      "58281432": "AMOS_ProV2_00_DirW",
      "0ff2ffc6": "AMOS_ProV2_00_LdirW_S",
      "12b9a7a2": "AMOS_ProV2_00_DirW_S",
      "d6a2911f": "AMOS_ProV2_00_Ldir",
      "aa4ed758": "AMOS_ProV2_00_Dir",
      "b4d46f0d": "AMOS_ProV2_00_Ldir_S",
      "a0896f98": "AMOS_ProV2_00_Dir_S_V",
      "21186468": "AMOS_ProV2_00_Fsel_S",
      "d8c41994": "AMOS_ProV2_00_Fsel_SS",
      "8822ca8c": "AMOS_ProV2_00_Fsel_SSS",
      "b23ec152": "AMOS_ProV2_00_Fsel_SSSS",
      "2970effb": "AMOS_ProV2_00__SaveRegs",
      "e8f1aa2b": "AMOS_ProV2_00__LoadRegs",
      "d937f0d6": "AMOS_ProV2_00_CommandLine_set",
      "97a3447b": "AMOS_ProV2_00_CommandLine_get",
      "bf660681": "AMOS_ProV2_00_Default",
      "b8c9794c": "AMOS_ProV2_00_Cls",
      "22cdab66": "AMOS_ProV2_00_Cls_I",
      "309cfc5c": "AMOS_ProV2_00_Cls_IIIII",
      "c4c8e928": "AMOS_ProV2_00_ScreenHeight",
      "a38e8b86": "AMOS_ProV2_00_ScreenHeight_I",
      "d0a0c1e2": "AMOS_ProV2_00_ScreenWidth",
      "0f9346a4": "AMOS_ProV2_00_ScreenWidth_I",
      "17a4ba07": "AMOS_ProV2_00_ScreenBase",
      "aaebc3b5": "AMOS_ProV2_00_ScreenColour",
      "32bdba41": "AMOS_ProV2_00_ScreenMode_I",
      "bfa08e91": "AMOS_ProV2_00_DisplayHeight",
      "65614205": "AMOS_ProV2_00_Ntsc",
      "4455994a": "AMOS_ProV2_00_Logbase",
      "4ff8cfeb": "AMOS_ProV2_00_Phybase",
      "42da694c": "AMOS_ProV2_00_DoubleBuffer",
      "a26fd6c2": "AMOS_ProV2_00_ScreenSwap",
      "1228169c": "AMOS_ProV2_00_ScreenSwap_I",
      "8d0d505c": "AMOS_ProV2_00_DualPlayfield",
      "8bc7e02f": "AMOS_ProV2_00_DualPriority",
      "30a5570c": "AMOS_ProV2_00_ScreenClone",
      "e771718a": "AMOS_ProV2_00_ScreenOpen",
      "f5e585f3": "AMOS_ProV2_00_ScreenClose",
      "79e7142c": "AMOS_ProV2_00_ScreenDisplay",
      "0a2327c3": "AMOS_ProV2_00_ScreenOffset",
      "c0e34229": "AMOS_ProV2_00_ScreenShow",
      "d6e17a45": "AMOS_ProV2_00_ScreenShow_I",
      "fb15dd66": "AMOS_ProV2_00_ScreenHide",
      "f46da08c": "AMOS_ProV2_00_ScreenHide_I",
      "a1e1dcc1": "AMOS_ProV2_00_AutoViewOn",
      "9a86e3da": "AMOS_ProV2_00_AutoViewOff",
      "1bccd343": "AMOS_ProV2_00_View",
      "97e4471c": "AMOS_ProV2_00_ScreenToFront",
      "a434493b": "AMOS_ProV2_00_ScreenToFront_I",
      "47c7f556": "AMOS_ProV2_00_ScreenToBack",
      "10dd4aac": "AMOS_ProV2_00_ScreenToBack_I",
      "7713c818": "AMOS_ProV2_00_Screen_I_V",
      "122ae746": "AMOS_ProV2_00_Screen__I",
      "6ec0cb83": "AMOS_ProV2_00_Hires",
      "f81ac00c": "AMOS_ProV2_00_Colour_II_V",
      "988dbecf": "AMOS_ProV2_00_Colour_I_I",
      "53dfc243": "AMOS_ProV2_00_ColourBack",
      "c01f5372": [
        ["match", "76ff"],
        "tail-call",
        ["match", "6100"],
        "follow-rel",
        ["match", "48e7 c000"],
        {
          "7001": "AMOS_ProV2_00_GetSpritePalette",
          "7002": "AMOS_ProV2_00_GetIconPalette"
        }
      ],
      "1485e966": [
        ["match", "6100"],
        "follow-rel",
        ["match", "48e7 c000"],
        {
          "7001": "AMOS_ProV2_00_GetSpritePalette_I",
          "7002": "AMOS_ProV2_00_GetIconPalette_I"
        }
      ],
      "bb933ef9": "AMOS_ProV2_00_GetPalette_I",
      "b718f7c7": "AMOS_ProV2_00_GetPalette_II",
      "db66b255": "AMOS_ProV2_00_FlashOff",
      "52d368fb": "AMOS_ProV2_00_Flash",
      "55c765ff": "AMOS_ProV2_00_ShiftOff",
      "3d7ed446": "AMOS_ProV2_00_ShiftUp",
      "adcbba86": "AMOS_ProV2_00_ShiftDown",
      "cc335638": "AMOS_ProV2_00_SetRainbow_IIISSS",
      "fa0ca706": "AMOS_ProV2_00_SetRainbow_IIISSSI",
      "27087628": "AMOS_ProV2_00_Rainbow",
      "2ff6f7e9": "AMOS_ProV2_00_RainbowDel",
      "31e4cf7b": "AMOS_ProV2_00_RainbowDel_I",
      "b1eb1505": "AMOS_ProV2_00_Rain_set_II",
      "d3fb9887": "AMOS_ProV2_00_Rain_get_II",
      "b3a1ae12": "AMOS_ProV2_00_CopperOn",
      "f188610e": "AMOS_ProV2_00_CopperOff",
      "307af9f1": "AMOS_ProV2_00_CopSwap",
      "84d57e8f": "AMOS_ProV2_00_CopReset",
      "6b0d713d": "AMOS_ProV2_00_CopWait_II",
      "a730a654": "AMOS_ProV2_00_CopWait_IIII",
      "5453fc36": "AMOS_ProV2_00_CopMove",
      "61f58e39": "AMOS_ProV2_00_CopMovel",
      "f44603c7": "AMOS_ProV2_00_CopLogic",
      "3d57ecef": "AMOS_ProV2_00_Autoback",
      "cd4ff268": "AMOS_ProV2_00_Plot_II",
      "f26ec5bd": "AMOS_ProV2_00_Plot_III",
      "934beec6": "AMOS_ProV2_00_Point",
      "7309d66e": "AMOS_ProV2_00_DrawTo",
      "3689f2ae": "AMOS_ProV2_00_Draw",
      "16a596a2": "AMOS_ProV2_00_Circle",
      "664baf5c": "AMOS_ProV2_00_Ellipse",
      "971bf536": "AMOS_ProV2_00_Xgr",
      "6ce6eb5a": "AMOS_ProV2_00_Ygr",
      "f1d37e85": "AMOS_ProV2_00_GrLocate",
      "29503b33": "AMOS_ProV2_00_Box",
      "3b1a6eff": "AMOS_ProV2_00_Clip_V",
      "55e4bb01": "AMOS_ProV2_00_Clip_IIII_V",
      "ae0e67b2": "AMOS_ProV2_00_GetRomFonts",
      "2e81d01e": "AMOS_ProV2_00_GetDiscFonts",
      "4728b0fc": "AMOS_ProV2_00_GetFonts",
      "56309916": "AMOS_ProV2_00_Font",
      "98872ae3": "AMOS_ProV2_00_SetFont",
      "72cf63b6": "AMOS_ProV2_00_Text",
      "6fe7dffd": "AMOS_ProV2_00_TextBase",
      "1bb1df0a": "AMOS_ProV2_00_TextLength",
      "0c7295c4": "AMOS_ProV2_00_TextStyles",
      "a2952fba": "AMOS_ProV2_00_SetText",
      "535c837b": "AMOS_ProV2_00_SetPattern",
      "478c9cdc": "AMOS_ProV2_00_SetPaint",
      "a46bda16": "AMOS_ProV2_00_Paint_II",
      "03539f66": "AMOS_ProV2_00_Paint_III",
      "ebea9536": "AMOS_ProV2_00_Bar",
      "a9f17df1": "AMOS_ProV2_00_SetTempras_I",
      "91f34897": "AMOS_ProV2_00_SetTempras",
      "4ec7ba45": "AMOS_ProV2_00_SetTempras_II",
      "16ca8aa1": "AMOS_ProV2_00_Ink_I",
      "894e9fbf": "AMOS_ProV2_00_Ink_II",
      "daef8d3c": "AMOS_ProV2_00_Ink_III",
      "3bc8f1a5": "AMOS_ProV2_00_GrWriting",
      "d2cac21a": "AMOS_ProV2_00_SetLine",
      "373bf5cd": "AMOS_ProV2_00_Hslider",
      "cfe292d1": "AMOS_ProV2_00_Vslider",
      "ff7e5b46": "AMOS_ProV2_00_SetSlider",
      "7de3014d": "AMOS_ProV2_00_DefScroll",
      "da347e87": "AMOS_ProV2_00_Scroll",
      "7bc040c5": "AMOS_ProV2_00_ScreenCopy_II",
      "2d4ecdc3": "AMOS_ProV2_00_ScreenCopy_III",
      "ee1d1cbf": "AMOS_ProV2_00_ScreenCopy_IIIIIIII",
      "20e20f11": "AMOS_ProV2_00_ScreenCopy_IIIIIIIII",
      "e7c88d11": "AMOS_ProV2_00_Physic_I",
      "5bdd4f9b": "AMOS_ProV2_00_Logic",
      "b971c514": "AMOS_ProV2_00_Logic_I",
      "c07a9d25": "AMOS_ProV2_00_Appear_III",
      "82669ea8": "AMOS_ProV2_00_Appear_IIII",
      "dfb5701b": "AMOS_ProV2_00_Zoom",
      "ef6164a8": "AMOS_ProV2_00_XHard_I",
      "1102711c": "AMOS_ProV2_00_XHard_II",
      "d7ea525a": "AMOS_ProV2_00_YHard_I",
      "80db4951": "AMOS_ProV2_00_YHard_II",
      "92461f60": "AMOS_ProV2_00_XScreen_I",
      "cb9a8d81": "AMOS_ProV2_00_XScreen_II",
      "101d007a": "AMOS_ProV2_00_YScreen_I",
      "817ed145": "AMOS_ProV2_00_YScreen_II",
      "ee76b07b": "AMOS_ProV2_00_XText",
      "5ff4c57d": "AMOS_ProV2_00_YText",
      "c691564a": "AMOS_ProV2_00_XGraphic",
      "310c9955": "AMOS_ProV2_00_YGraphic",
      "154d8a2a": "AMOS_ProV2_00_ReserveZone",
      "69ba7481": "AMOS_ProV2_00_ReserveZone_I",
      "9d6b8d72": "AMOS_ProV2_00_ResetZone",
      "eef9fcbe": "AMOS_ProV2_00_ResetZone_I",
      "eb52ded1": "AMOS_ProV2_00_SetZone",
      "c6c0795a": "AMOS_ProV2_00_Zone_II_I",
      "0a508979": "AMOS_ProV2_00_Zone_III_I",
      "b997d6bd": "AMOS_ProV2_00_Hzone_II",
      "6d56fb3a": "AMOS_ProV2_00_Hzone_III",
      "833e1935": "AMOS_ProV2_00_Scin_II",
      "67f6ca17": "AMOS_ProV2_00_Scin_III",
      "7ddd3571": "AMOS_ProV2_00_MouseScreen",
      "8666d771": "AMOS_ProV2_00_MouseZone",
      "2aa93527": "AMOS_ProV2_00_GetCblock",
      "fcdab786": "AMOS_ProV2_00_PutCblock_I",
      "d025f1c3": "AMOS_ProV2_00_PutCblock_III",
      "07cc1fbc": "AMOS_ProV2_00_DelCblock",
      "1c522dfb": "AMOS_ProV2_00_DelCblock_I",
      "1be177bc": "AMOS_ProV2_00_GetBlock_IIIII",
      "51f1a6e7": "AMOS_ProV2_00_GetBlock_IIIIII",
      "c37603e4": "AMOS_ProV2_00_PutBlock_I",
      "cfd1e7bf": "AMOS_ProV2_00_PutBlock_III",
      "9597fd3d": "AMOS_ProV2_00_PutBlock_IIII",
      "cc278afe": "AMOS_ProV2_00_PutBlock_IIIII",
      "d47067c4": "AMOS_ProV2_00_DelBlock",
      "0baae91c": "AMOS_ProV2_00_DelBlock_I",
      "75fadb11": "AMOS_ProV2_00_HrevBlock",
      "b36aa37e": "AMOS_ProV2_00_VrevBlock",
      "be669b59": "AMOS_ProV2_00_CloseWorkbench",
      "dffd0211": "AMOS_ProV2_00_AmosToFront",
      "42fc4b5e": "AMOS_ProV2_00_AmosToBack",
      "1c48a269": "AMOS_ProV2_00_AmosHere",
      "781c6fc2": "AMOS_ProV2_00_AmosLock",
      "bd5f494f": "AMOS_ProV2_00_AmosUnlock",
      "4a776d59": "AMOS_ProV2_00_Error",
      "e97994b7": "AMOS_ProV2_00_UpdateOff",
      "bb0c5dee": "AMOS_ProV2_00_UpdateOn",
      "b360514b": "AMOS_ProV2_00_Update",
      "bb263a3e": "AMOS_ProV2_00_BobUpdateOff",
      "ec69b1a8": "AMOS_ProV2_00_BobUpdateOn",
      "cc4a87c3": "AMOS_ProV2_00_BobUpdate",
      "e929b59a": "AMOS_ProV2_00_SpriteUpdateOff",
      "8a467571": "AMOS_ProV2_00_SpriteUpdateOn",
      "97635dc8": "AMOS_ProV2_00_SpriteUpdate",
      "58d6e4f0": "AMOS_ProV2_00_UpdateEvery",
      "4c4f3886": "AMOS_ProV2_00_BobClear",
      "a3d3dcc6": "AMOS_ProV2_00_BobDraw",
      "d12369b9": "AMOS_ProV2_00_LimitBob",
      "2c6b8eb3": "AMOS_ProV2_00_LimitBob_IIII",
      "e8352325": "AMOS_ProV2_00_LimitBob_IIIII",
      "6ab2e6bc": "AMOS_ProV2_00_PriorityOn",
      "29a8acb4": "AMOS_ProV2_00_PriorityOff",
      "b085f8cf": "AMOS_ProV2_00_PriorityReverseOn",
      "6961fac0": "AMOS_ProV2_00_PriorityReverseOff",
      "34f1ba86": "AMOS_ProV2_00_Amalerr",
      "3493b2a2": "AMOS_ProV2_00_Freeze_V",
      "e1ca0549": "AMOS_ProV2_00_Unfreeze",
      "96cc1ec0": "AMOS_ProV2_00_SynchroOn",
      "8fede65e": "AMOS_ProV2_00_SynchroOff",
      "465f6fea": "AMOS_ProV2_00_Synchro",
      "7a7ec055": "AMOS_ProV2_00_AmalOn",
      "b215599f": "AMOS_ProV2_00_AmalOff",
      "85452de5": "AMOS_ProV2_00_AmalFreeze",
      "b2f775cb": "AMOS_ProV2_00_MoveOn",
      "465218e6": "AMOS_ProV2_00_AnimOn",
      "2d53ed68": "AMOS_ProV2_00_MoveOff",
      "398593fa": "AMOS_ProV2_00_AnimOff",
      "72b8df60": "AMOS_ProV2_00_MoveFreeze",
      "013c5193": "AMOS_ProV2_00_AnimFreeze",
      "46daba7b": "AMOS_ProV2_00_AmalOn_I",
      "042de85e": "AMOS_ProV2_00_AmalOff_I",
      "56f79f12": "AMOS_ProV2_00_AmalFreeze_I",
      "13c358c3": "AMOS_ProV2_00_MoveOn_I",
      "f8e9bede": "AMOS_ProV2_00_AnimOn_I",
      "f09267c6": "AMOS_ProV2_00_MoveOff_I",
      "1798362d": "AMOS_ProV2_00_AnimOff_I",
      "815ae018": "AMOS_ProV2_00_MoveFreeze_I",
      "67bcf2ec": "AMOS_ProV2_00_AnimFreeze_I",
      "453fd095": "AMOS_ProV2_00_MoveX_ISI",
      "b39be9b6": "AMOS_ProV2_00_MoveY_ISI",
      "07d2d614": "AMOS_ProV2_00_Amal_ISI",
      "264c11ef": "AMOS_ProV2_00_MoveX_IS",
      "ac0b684b": "AMOS_ProV2_00_MoveY_IS",
      "2f703808": "AMOS_ProV2_00_Amal_IS",
      "a2067f95": "AMOS_ProV2_00_Anim_IS",
      "1ea2231a": "AMOS_ProV2_00_Movon",
      "1b8cf36d": "AMOS_ProV2_00_Chanan",
      "2aab5101": "AMOS_ProV2_00_Chanmv",
      "8654edb7": "AMOS_ProV2_00_Amreg_set_I",
      "50a9b6f6": "AMOS_ProV2_00_Amreg_get_I",
      "f989e1d5": "AMOS_ProV2_00_Amreg_set_II",
      "e8e35061": "AMOS_ProV2_00_Amreg_get_II",
      "a2373f7c": "AMOS_ProV2_00_Amplay_II",
      "f194f423": "AMOS_ProV2_00_Amplay_IIII",
      "b364f0e5": "AMOS_ProV2_00_XBob",
      "a5d7a519": "AMOS_ProV2_00_YBob",
      "ba5c2073": "AMOS_ProV2_00_XSprite",
      "47c0c0a9": "AMOS_ProV2_00_YSprite",
      "473cfc64": "AMOS_ProV2_00_IBob",
      "e1572aa3": "AMOS_ProV2_00_ISprite",
      "e430cfb8": "AMOS_ProV2_00_XMouse_set",
      "346ce996": "AMOS_ProV2_00_XMouse_get",
      "5345b8a7": "AMOS_ProV2_00_YMouse_set",
      "8ee5bfcd": "AMOS_ProV2_00_YMouse_get",
      "24703f15": "AMOS_ProV2_00_MouseKey",
      "af5448a8": "AMOS_ProV2_00_MouseClick",
      "c773f53d": "AMOS_ProV2_00_Hide",
      "11bd0051": "AMOS_ProV2_00_HideOn",
      "c546e8b1": "AMOS_ProV2_00_Show",
      "5dc83ed1": "AMOS_ProV2_00_ShowOn",
      "480de4e8": "AMOS_ProV2_00_LimitMouse",
      "dc87d840": "AMOS_ProV2_00_LimitMouse_I",
      "0a99ed54": "AMOS_ProV2_00_LimitMouse_IIII",
      "69f4c735": "AMOS_ProV2_00_ChangeMouse",
      "363fd370": "AMOS_ProV2_00_SetBob",
      "64a4b3ea": "AMOS_ProV2_00_Bob",
      "27c8a9aa": "AMOS_ProV2_00_BobOff",
      "13d3e9df": "AMOS_ProV2_00_BobOff_I",
      "be3852ed": "AMOS_ProV2_00_SetSpriteBuffer",
      "6ff08421": "AMOS_ProV2_00_SpritePriority",
      "2e18ddec": "AMOS_ProV2_00_Sprite",
      "269d135e": "AMOS_ProV2_00_SpriteOff",
      "5a0c61da": "AMOS_ProV2_00_SpriteOff_I",
      "fba5f8a8": "AMOS_ProV2_00_SetHardcol",
      "38de4d34": "AMOS_ProV2_00_Hardcol",
      "52b06ab3": "AMOS_ProV2_00_BobspriteCol_I",
      "04b07ece": "AMOS_ProV2_00_BobspriteCol_III",
      "3c349f40": "AMOS_ProV2_00_BobCol_I",
      "06795787": "AMOS_ProV2_00_BobCol_III",
      "a21dd061": "AMOS_ProV2_00_SpritebobCol_I",
      "03ea26cc": "AMOS_ProV2_00_SpritebobCol_III",
      "9e045ebd": "AMOS_ProV2_00_SpriteCol_I",
      "8cd69f32": "AMOS_ProV2_00_SpriteCol_III",
      "66982d60": "AMOS_ProV2_00_Col_I_I",
      "dd47afd3": [
        ["match", "7201 6100"],
        "follow-rel",
        ["match", "0281 0000 3fff 6700"],
        ["skip", 1],
        ["match", "2001 6100"],
        "follow-rel",
        ["match", "7200 6100"],
        "follow-rel",
        ["match", "48e7 c000"],
        {
          "7001": "AMOS_ProV2_00_MakeMask",
          "7002": "AMOS_ProV2_00_MakeIconMask"
        }
      ],
      "90b56dd5": [
        ["match", "2203 6100"],
        "follow-rel",
        ["match", "0281 0000 3fff 6700"],
        ["skip", 1],
        ["match", "2001 6100"],
        "follow-rel",
        ["match", "7200 6100"],
        "follow-rel",
        ["match", "48e7 c000"],
        {
          "7001": "AMOS_ProV2_00_MakeMask_I",
          "7002": "AMOS_ProV2_00_MakeIconMask_I"
        }
      ],
      "46551b5f": [
        ["match", "7201 6100"],
        "follow-rel",
        ["match", "0281 0000 3fff 6700"],
        ["skip", 1],
        ["match", "2001 6100"],
        "follow-rel",
        ["match", "7200 6100"],
        "follow-rel",
        ["match", "48e7 c000"],
        {
          "7001": "AMOS_ProV2_00_NoMask",
          "7002": "AMOS_ProV2_00_NoIconMask"
        }
      ],
      "b054b4c4": [
        ["match", "2203 6100"],
        "follow-rel",
        ["match", "0281 0000 3fff 6700"],
        ["skip", 1],
        ["match", "2001 6100"],
        "follow-rel",
        ["match", "7200 6100"],
        "follow-rel",
        ["match", "48e7 c000"],
        {
          "7001": "AMOS_ProV2_00_NoMask_I",
          "7002": "AMOS_ProV2_00_NoIconMask_I"
        }
      ],
      "57751dc3": "AMOS_ProV2_00_HotSpot_III",
      "65b1bc59": "AMOS_ProV2_00_HotSpot_II",
      "ae28daeb": [
        ["match", "222b 0010 206d fff8 4ea8 0080 6700"],
        ["skip", 1],
        ["match", "2f00 2040 6100"],
        ["skip", 1],
        ["match", "2753 0004 588b"],
        "tail-call",
        ["match", "2013 6f00"],
        ["skip", 1],
        ["match", "6100"],
        "follow-rel",
        ["match", "7200 6100"],
        "follow-rel",
        ["match", "48e7 c000"],
        {
          "7001": "AMOS_ProV2_00_GetSprite_IIIIII",
          "7002": "AMOS_ProV2_00_GetIcon_IIIIII"
        }
      ],
      "3548d633": [
        ["match", "206d 052c 2f08 6700"],
        ["skip", 1],
        ["match", "6100"],
        ["skip", 1],
        "tail-call",
        ["match", "2013 6f00"],
        ["skip", 1],
        ["match", "6100"],
        "follow-rel",
        ["match", "7200 6100"],
        "follow-rel",
        {
          "48e7 c000 7001 6100": "AMOS_ProV2_00_GetSprite_IIIII",
          "48e7 c000 7002 6100": "AMOS_ProV2_00_GetIcon_IIIII"
        }
      ],
      "9fd206d6": "AMOS_ProV2_00_PutBob",
      "1232c010": "AMOS_ProV2_00_Hrev",
      "69613c20": "AMOS_ProV2_00_Vrev",
      "f278c64e": "AMOS_ProV2_00_Rev",
      "784a2e0c": "AMOS_ProV2_00_PasteBob",
      "727f91d3": "AMOS_ProV2_00_PasteIcon",
      "5c3b0ba9": [
        ["match", "41f9"],
        "follow-abs",
        ["match", "0281 0000 3fff 6700"],
        ["skip", 1],
        ["match", "2001 6100"],
        "follow-rel",
        ["match", "7200 6100"],
        "follow-rel",
        {
          "48e7 c000 7001 6100": "AMOS_ProV2_00_SpriteBase",
          "48e7 c000 7002 6100": "AMOS_ProV2_00_IconBase"
        }
      ],
      "282c809d": "AMOS_ProV2_00_Using",
      "5520712a": "AMOS_ProV2_00_Stop",
      "9a5617bd": "AMOS_ProV2_00_WindOpen_IIIII",
      "00db2da7": "AMOS_ProV2_00_WindOpen_IIIIII",
      "93961874": "AMOS_ProV2_00_WindOpen_IIIIIII",
      "61648e08": "AMOS_ProV2_00_WindSave",
      "f9adf824": "AMOS_ProV2_00_WindMove",
      "e577a135": "AMOS_ProV2_00_WindSize_II",
      "183ad77c": "AMOS_ProV2_00_WindClose",
      "243db969": "AMOS_ProV2_00_Window",
      "a7fcc8db": "AMOS_ProV2_00_Windon",
      "a3b0e7bc": "AMOS_ProV2_00_Writing_I",
      "99590b0a": "AMOS_ProV2_00_Writing_II",
      "b2c18022": "AMOS_ProV2_00_Border_III_V",
      "0624024d": "AMOS_ProV2_00_TitleTop",
      "429749cc": "AMOS_ProV2_00_TitleBottom",
      "de1be837": "AMOS_ProV2_00_XCurs",
      "826412be": "AMOS_ProV2_00_YCurs",
      "9a78e79c": "AMOS_ProV2_00_SetCurs",
      "25e946d3": "AMOS_ProV2_00_Locate",
      "8c8d2093": "AMOS_ProV2_00_Centre",
      "2fd4389d": "AMOS_ProV2_00_Cmove_II_V",
      "9e118ced": [
        ["match", "43fa 0006 6000"],
        ["skip", 1],
        {
          "1b42": "AMOS_ProV2_00_Paper_I_V",
          "1b44": "AMOS_ProV2_00_CursPen",
          "1b50": "AMOS_ProV2_00_Pen_I_V"
        }
      ],
      "0c8e01c2": [
        ["match", "43fa 0006 6000"],
        ["skip", 1],
        {
          "0c00": "AMOS_ProV2_00_Home",
          "1900": "AMOS_ProV2_00_Clw",
          "1a00": "AMOS_ProV2_00_Cline_V",
          "1b43": {
            "3000": "AMOS_ProV2_00_CursOff",
            "3100": "AMOS_ProV2_00_CursOn"
          },
          "1b49": {
            "3000": "AMOS_ProV2_00_InverseOff",
            "3100": "AMOS_ProV2_00_InverseOn"
          },
          "1b4d": {
            "3000": "AMOS_ProV2_00_MemorizeX",
            "3100": "AMOS_ProV2_00_RememberX",
            "3200": "AMOS_ProV2_00_MemorizeY",
            "3300": "AMOS_ProV2_00_RememberY"
          },
          "1b53": {
            "3000": "AMOS_ProV2_00_ShadeOff",
            "3100": "AMOS_ProV2_00_ShadeOn"
          },
          "1b55": {
            "3000": "AMOS_ProV2_00_UnderOff",
            "3100": "AMOS_ProV2_00_UnderOn"
          },
          "1b56": {
            "3000": "AMOS_ProV2_00_ScrollOff",
            "3100": "AMOS_ProV2_00_ScrollOn"
          },
          "1c00": "AMOS_ProV2_00_Cright_V",
          "1d00": "AMOS_ProV2_00_Cleft_V",
          "1e00": "AMOS_ProV2_00_Cup_V",
          "1f00": "AMOS_ProV2_00_Cdown_V"
        }
      ],
      "b8fe4022": "AMOS_ProV2_00_Cline_I_V",
      "97c63b3e": [
        ["match", "43fa 0006 6000"],
        ["skip", 1],
        {
          "1000": "AMOS_ProV2_00_Hscroll",
          "1400": "AMOS_ProV2_00_Vscroll"
        }
      ],
      "6a4409c4": "AMOS_ProV2_00_SetTab",
      "1e97446c": "AMOS_ProV2_00_Free_I",
      "dbe60d28": "AMOS_ProV2_00_Inkey",
      "3554a54c": "AMOS_ProV2_00_Scancode",
      "bb56f06b": "AMOS_ProV2_00_Scanshift",
      "b42fdb31": "AMOS_ProV2_00_KeyState",
      "e67d1224": "AMOS_ProV2_00_KeyShift",
      "f4c3d259": "AMOS_ProV2_00_Joy",
      "aba7e887": "AMOS_ProV2_00_Jup",
      "91dc64e4": "AMOS_ProV2_00_Jdown",
      "a497e3a6": "AMOS_ProV2_00_Jleft",
      "cb87e3d0": "AMOS_ProV2_00_Jright",
      "b6bc62b9": "AMOS_ProV2_00_Fire",
      "cccd87fc": "AMOS_ProV2_00_PutKey",
      "f71eae6c": "AMOS_ProV2_00_ClearKey",
      "1264c536": "AMOS_ProV2_00_Key_set_I",
      "f812ffa6": "AMOS_ProV2_00_Key_get_I",
      "5c6364b2": "AMOS_ProV2_00_Scan_I",
      "b1ca97a4": "AMOS_ProV2_00_Scan_II",
      "d14613fc": "AMOS_ProV2_00_Instr_SS",
      "b225acc1": "AMOS_ProV2_00_Instr_SSI",
      "71460d05": "AMOS_ProV2_00_Flip",
      "65decfb5": "AMOS_ProV2_00_Len",
      "59f60d16": "AMOS_ProV2_00_Space",
      "033bc0a5": "AMOS_ProV2_00_String",
      "28dd3607": "AMOS_ProV2_00_Chr",
      "1b016f0c": "AMOS_ProV2_00_Tab",
      "4ef2621f": "AMOS_ProV2_00_Cleft_S",
      "0c1da394": "AMOS_ProV2_00_Cright_S",
      "f412fcda": "AMOS_ProV2_00_Cup_S",
      "122461b3": "AMOS_ProV2_00_Cdown_S",
      "f49966c6": [
        ["match", "45fa 0006 6000"],
        ["skip", 1],
        {
          "1b42": "AMOS_ProV2_00_Paper_I_S",
          "1b50": "AMOS_ProV2_00_Pen_I_S"
        }
      ],
      "31502663": "AMOS_ProV2_00_At",
      "4b310fc6": "AMOS_ProV2_00_Cmove_II_S",
      "4d57fa3d": [
        ["match", "4a83 6700"],
        ["skip", 1],
        ["match", "b6bc 0000 00cf 6400"],
        ["skip", 1],
        ["match", "41fa 0006 6000"],
        ["skip", 1],
        {
          "1b52": "AMOS_ProV2_00_Repeat",
          "1b5a": "AMOS_ProV2_00_Zone_SI_S"
        }
      ],
      "e4dea3b2": "AMOS_ProV2_00_Border_SI_S",
      "53c3290a": "AMOS_ProV2_00_Lower",
      "e80eca49": "AMOS_ProV2_00_Upper",
      "bd2f3572": "AMOS_ProV2_00_Asc",
      "b0080d15": "AMOS_ProV2_00_Bin_I",
      "40d397c0": "AMOS_ProV2_00_Bin_II",
      "46de5fd2": "AMOS_ProV2_00_Hex_I",
      "8357d541": "AMOS_ProV2_00_Hex_II",
      "3fc50ebc": "AMOS_ProV2_00_DialogOpen_IS",
      "148f729c": "AMOS_ProV2_00_DialogOpen_ISI",
      "67e945c6": "AMOS_ProV2_00_DialogOpen_ISII",
      "6c5949fc": "AMOS_ProV2_00_Edialog",
      "c919c4d4": "AMOS_ProV2_00_DialogClose",
      "b77a4565": [
        ["match", "2003 6f00"],
        ["skip", 1],
        ["match", "4eb9"],
        "follow-abs",
        {
          "48e7": "AMOS_ProV2_00_DialogClose_I",
          "6100": "AMOS_ProV2_00_DialogClr"
        }
      ],
      "5fa757f7": "AMOS_ProV2_00_DialogFreeze",
      "e5dc279c": "AMOS_ProV2_00_DialogFreeze_I",
      "634f897b": "AMOS_ProV2_00_DialogUnfreeze",
      "57198807": "AMOS_ProV2_00_DialogUnfreeze_I",
      "828d6547": "AMOS_ProV2_00_DialogUpdate_II",
      "f5527a2f": "AMOS_ProV2_00_DialogUpdate_IIS",
      "5ff17af9": "AMOS_ProV2_00_DialogUpdate_IISI",
      "4033ea8b": "AMOS_ProV2_00_DialogUpdate_IISII",
      "6e9fac3a": "AMOS_ProV2_00_DialogRun_I",
      "9d082489": "AMOS_ProV2_00_DialogRun_II",
      "1cd1b85d": "AMOS_ProV2_00_DialogRun_IIII",
      "51c544c3": "AMOS_ProV2_00_Dialog",
      "0c8d52eb": "AMOS_ProV2_00_Vdialog_set_II_X[I and S undifferentiable]",
      "40e4a851": "AMOS_ProV2_00_Vdialog_get_II_X[I and S undifferentiable]",
      "8ac06d45": "AMOS_ProV2_00_Rdialog_II_I",
      "bc0bf2ed": "AMOS_ProV2_00_Rdialog_III_I",
      "9b9d9a14": "AMOS_ProV2_00_Rdialog_II_S",
      "4a0ddb0f": "AMOS_ProV2_00_Rdialog_III_S",
      "ecd71371": "AMOS_ProV2_00_Zdialog",
      "2924bdea": "AMOS_ProV2_00_DialogBox_S",
      "f9234b42": "AMOS_ProV2_00_DialogBox_SI",
      "7eb854ba": "AMOS_ProV2_00_DialogBox_SIS",
      "2df0c633": "AMOS_ProV2_00_DialogBox_SISII",
      "10537001": "AMOS_ProV2_00_ReadText_S",
      "8946b6d6": "AMOS_ProV2_00_ReadText_SII",
      "f142a0cb": "AMOS_ProV2_00_ResourceScreenOpen",
      "4e01f791": "AMOS_ProV2_00_ResourceBank",
      "fbd4a5e0": "AMOS_ProV2_00_ResourceUnpack",
      "4575e79d": "AMOS_ProV2_00_ArexxExist",
      "cb056ebc": "AMOS_ProV2_00_ArexxOpen",
      "7f72f279": "AMOS_ProV2_00_Arexx__I",
      "848d4405": "AMOS_ProV2_00_ArexxWait",
      "de6d51e9": "AMOS_ProV2_00_ArexxClose",
      "59b8bb52": "AMOS_ProV2_00_Arexx_I_S",
      "4efb12dc": "AMOS_ProV2_00_ArexxAnswer_I",
      "708c8eb5": "AMOS_ProV2_00_ArexxAnswer_IS",
      "0c1d1f9d": "AMOS_ProV2_00_OnMenuOn",
      "849d884c": "AMOS_ProV2_00_MenuToBank",
      "1fcf9c2f": "AMOS_ProV2_00_BankToMenu",
      "34124a81": "AMOS_ProV2_00_MenuOn",
      "2ebbff09": "AMOS_ProV2_00_MenuOff",
      "cb83b8d9": "AMOS_ProV2_00_MenuMouseOn",
      "ae32d179": "AMOS_ProV2_00_MenuMouseOff",
      "2033d54a": "AMOS_ProV2_00_MenuBase",
      "af3e7bb6": "AMOS_ProV2_00_XMenu",
      "993af0c4": "AMOS_ProV2_00_YMenu",
      "cc870a1a": "AMOS_ProV2_00_Choice",
      "c99f3ddd": "AMOS_ProV2_00_Choice_I",
      "d2fa4f27": "AMOS_ProV2_00_MenuBar",
      "e9824fe8": "AMOS_ProV2_00_MenuLine",
      "d2673c71": "AMOS_ProV2_00_MenuTline",
      "24b4d743": "AMOS_ProV2_00_MenuMovable",
      "87c6c6be": "AMOS_ProV2_00_MenuStatic",
      "63416778": "AMOS_ProV2_00_MenuItemMovable",
      "aa6b7e5f": "AMOS_ProV2_00_MenuItemStatic",
      "a46b90a4": "AMOS_ProV2_00_MenuActive",
      "c165ab22": "AMOS_ProV2_00_MenuInactive",
      "746a5daf": "AMOS_ProV2_00_MenuSeparate",
      "dec69b32": "AMOS_ProV2_00_MenuLink",
      "a54dfb02": "AMOS_ProV2_00_MenuCalled",
      "2d078ba2": "AMOS_ProV2_00_MenuOnceV",
      "dbf7ff6f": "AMOS_ProV2_00_MenuCalc",
      "738ece00": "Compact_ProV2_00_Pack_II",
      "0c57b4fd": "Compact_ProV2_00_Pack_IIIIII",
      "77e8141d": "Compact_ProV2_00_Spack_II",
      "337a52ad": "Compact_ProV2_00_Spack_IIIIII",
      "168ef616": "Compact_ProV2_00_Unpack_I",
      "7e174f9b": "Compact_ProV2_00_Unpack_III",
      "b09ff1e5": "Compact_ProV2_00_Unpack_II",
      "c08c3b01": "Music_ProV2_00_Say_SI",
      "46877ee0": "Music_ProV2_00_Say_S",
      "d0825d53": "Music_ProV2_00_SetTalk",
      "cfaa65cb": "Music_ProV2_00_MouthWidth",
      "bb2b94f3": "Music_ProV2_00_MouthHeight",
      "4974e01d": "Music_ProV2_00_Bell",
      "bb999211": "Music_ProV2_00_Bell_I",
      "0b7b3c72": "Music_ProV2_00_Boom",
      "92536c2b": "Music_ProV2_00_Shoot",
      "fd8f3c8c": "Music_ProV2_00_Volume_I",
      "29facb90": "Music_ProV2_00_Volume_II",
      "1364cc1a": "Music_ProV2_00_TalkStop",
      "4a1e1a5a": "Music_ProV2_00_Play_II",
      "90a49e7c": "Music_ProV2_00_Play_III",
      "38d810bf": "Music_ProV2_00_PlayOff",
      "2ab33238": "Music_ProV2_00_PlayOff_I",
      "3a7570aa": "Music_ProV2_00_SamBank",
      "6f2e3ed7": "Music_ProV2_00_SamLoopOn",
      "ea00c97a": "Music_ProV2_00_SamLoopOn2",
      "af168fbd": "Music_ProV2_00_SamLoopOff",
      "918e4a9f": "Music_ProV2_00_NoiseTo",
      "359b168f": "Music_ProV2_00_Sample",
      "6e8db8f8": "Music_ProV2_00_SamPlay_I",
      "d09e4a3d": "Music_ProV2_00_SamPlay_II",
      "b0debcd3": "Music_ProV2_00_SamPlay_III",
      "5325a43c": "Music_ProV2_00_SamRaw",
      "56ae5fd6": "Music_ProV2_00_Sload",
      "f64fa0dd": "Music_ProV2_00_Wave",
      "0bc0e08e": "Music_ProV2_00_SetWave",
      "ce739e53": "Music_ProV2_00_DelWave",
      "0573c925": "Music_ProV2_00_SetEnvel",
      "557a4772": "Music_ProV2_00_MusicOff",
      "589ed689": "Music_ProV2_00_MusicStop",
      "e744b983": "Music_ProV2_00_Voice",
      "fcbf7440": "Music_ProV2_00_Music",
      "2df33e7b": "Music_ProV2_00_Tempo",
      "4db09473": "Music_ProV2_00_Vumeter",
      "50336477": "Music_ProV2_00_Mubase",
      "9e5268fd": "Music_ProV2_00_LedOn",
      "3a2499c7": "Music_ProV2_00_LedOff",
      "f77572c1": "Music_ProV2_00_SamSwapped",
      "15f92bfe": "Music_ProV2_00_SamSwap",
      "7ca05843": "Music_ProV2_00_SamStop",
      "7486d619": "Music_ProV2_00_SamStop_I",
      "11eaed12": "Music_ProV2_00_TrackLoad",
      "fe916243": "Music_ProV2_00_TrackStop",
      "d950339d": "Music_ProV2_00_TrackLoopOn",
      "2d697eac": "Music_ProV2_00_TrackLoopOf",
      "3ded1e9b": "Music_ProV2_00_TrackPlay",
      "d5b6d2bc": "Music_ProV2_00_TrackPlay_I",
      "0aaadcc0": "Music_ProV2_00_TrackPlay_II",
      "219f5036": "Music_ProV2_00_MouthRead",
      "5e832b51": "Music_ProV2_00_TalkMisc",
      "72b7e908": "Music_ProV2_00_Ssave",
      "b8453ce1": "Music_ProV2_00_MedLoad",
      "5a111eeb": "Music_ProV2_00_MedStop",
      "0ecc0c63": "Music_ProV2_00_MedPlay",
      "fbd9d462": "Music_ProV2_00_MedPlay_I",
      "7eeafd85": "Music_ProV2_00_MedPlay_II",
      "5ee33f3f": "Music_ProV2_00_MedMidiOn",
      "6cea64bf": "Music_ProV2_00_MedCont",
      "else": {
        "2003 b0bc 0000 0040 6500": "Music_ProV2_00_Mvolume"
      }
    }]
  ]
}
